<?xml version="1.0"?>
<xml-inputs priority="370" xmlns="http://axelor.com/xml/ns/data-import"
            xmlns:xsi="http://www.w3.org/2001/XMLSchema-instance"
            xsi:schemaLocation="http://axelor.com/xml/ns/data-import
  https://axelor.com/xml/ns/data-import/data-import_7.4.xsd">


    <input file="grupos.xml" root="datos">
        <bind node="grupos/grupo" type="com.educaflow.apps.sistemaeducativo.db.Grupo" search="self.code = :code"  create="true">
            <bind node="@code" to="code" />
            <bind node="@name" to="name" />
            <bind node="modulos/modulo" to="modulos" search="self.code = :code" create="false">
                <bind node="@code" to="code" />
            </bind>
        </bind>
    </input>

</xml-inputs>